pynews/__init__.py
pynews/__main__.py
pynews/constants.py
pynews/parser.py
pynews/pynews.py
pynews/utils.py
PyNews-0.3.0.dist-info/LICENSE
PyNews-0.3.0.dist-info/METADATA
PyNews-0.3.0.dist-info/WHEEL
PyNews-0.3.0.dist-info/entry_points.txt
PyNews-0.3.0.dist-info/top_level.txt
PyNews-0.3.0.dist-info/RECORD
