Metadata-Version: 2.1
Name: PyNews
Version: 0.3.0
Summary: PyNews is a simple Python CLI to browse news from HN website
Home-page: https://github.com/mazulo/pynews_cli
Download-URL: https://github.com/mazulo/pynews_cli/archive/master.zip
Author: Patrick Mazulo
Author-email: pmazulo@gmail.com
Maintainer: Patrick Mazulo
Maintainer-email: pmazulo@gmail.com
License: MIT
Keywords: pynews cli shell news hackernews
Platform: windows linux
Classifier: Intended Audience :: Developers
Classifier: Development Status :: 5 - Production/Stable
Classifier: Environment :: Console
Classifier: License :: OSI Approved :: GNU General Public License v3 (GPLv3)
Classifier: Operating System :: OS Independent
Classifier: Programming Language :: Python :: 3
Classifier: Programming Language :: Python :: 3.7
Classifier: Programming Language :: Python :: 3.8
Classifier: Programming Language :: Python :: 3.9
Classifier: Programming Language :: Python :: 3.10
Classifier: Topic :: Utilities
Classifier: Topic :: System :: Shells
License-File: LICENSE
Requires-Dist: curses-menu (==0.6.7)
Requires-Dist: requests (==2.28.1)
Requires-Dist: alive-progress (==2.4.1)
